
    <rigidbody2d_scene>
    
      <camera center="0 0" scale="8.3225" fps="50" render_at_fps="0" locked="0"/>
    
      <integrator type="symplectic_euler" dt="0.01"/>
    
      <impact_operator type="gr" CoR="1.0" v_tol="1.0e-9" cache_impulses="0">
        <solver name="lcp_solver_isaiah_debug" linear_solvers="ma27 ma86" max_iters="100" tol="1.0e-9"/>
      </impact_operator>
    
      <near_earth_gravity f="0.0 0.0"/>
    
    
      <geometry type="circle" r="1"/>
    
      <rigid_body x="0.008104471275535794 0.006825915637293643" theta="1.570796326794897" v="0.025176672296408853 0.21063271146595386" omega="0" rho="8.0" r="1" geo_idx="0"/>
  <rigid_body x="0.00523328524803347 0.10066035470397446" theta="1.570796326794897" v="-0.2852814860014159 -0.10568444700221247" omega="0" rho="8.0" r="1" geo_idx="0"/>
  <rigid_body x="0.0033157025772235327 0.20840600669950585" theta="1.570796326794897" v="0.681745948069113 0.7551362031205722" omega="0" rho="8.0" r="1" geo_idx="0"/>
  <rigid_body x="0.10043236468937293 0.0019890040258353724" theta="1.570796326794897" v="0.9800714890317097 0.4631295726579163" omega="0" rho="8.0" r="1" geo_idx="0"/>
  <rigid_body x="0.10998684130528323 0.10432764353765159" theta="1.570796326794897" v="0.6170756518956091 0.23186261840484002" omega="0" rho="8.0" r="1" geo_idx="0"/>
  <rigid_body x="0.10861900677951576 0.2014542958938691" theta="1.570796326794897" v="-0.618980026901107 0.6917844890223357" omega="0" rho="8.0" r="1" geo_idx="0"/>
  <rigid_body x="0.20695277625540648 0.008170940443670543" theta="1.570796326794897" v="0.030696777041424372 0.9736163944500178" omega="0" rho="8.0" r="1" geo_idx="0"/>
  <rigid_body x="0.2027357274226903 0.10104848628554566" theta="1.570796326794897" v="0.9952294665010919 -0.09369413259262926" omega="0" rho="8.0" r="1" geo_idx="0"/>
  <rigid_body x="0.20408923397192164 0.20494202407363293" theta="1.570796326794897" v="0.7525427422239432 -0.7461947248434657" omega="0" rho="8.0" r="1" geo_idx="0"/>
    
    </rigidbody2d_scene>
    