
    <rigidbody2d_scene>
    
      <camera center="0 0" scale="8.3225" fps="50" render_at_fps="0" locked="0"/>
    
      <integrator type="symplectic_euler" dt="0.01"/>
    
      <impact_operator type="gr" CoR="1.0" v_tol="1.0e-9" cache_impulses="0">
        <solver name="lcp_solver_isaiah_debug" linear_solvers="ma27 ma86" max_iters="100" tol="1.0e-9"/>
      </impact_operator>
    
      <near_earth_gravity f="0.0 0.0"/>
    
    
      <geometry type="circle" r="1"/>
    
      <rigid_body x="0.0002462467753324504 0.003679465399072871" theta="1.570796326794897" v="0.0728139882032055 0.5806597748918567" omega="0" rho="8.0" r="1" geo_idx="0"/>
  <rigid_body x="0.0012530137486820225 0.10630514290849094" theta="1.570796326794897" v="0.440729157792066 0.6718210618555185" omega="0" rho="8.0" r="1" geo_idx="0"/>
  <rigid_body x="0.00998886534279239 0.2039298235273685" theta="1.570796326794897" v="-0.7333566426692464 -0.013810839537166997" omega="0" rho="8.0" r="1" geo_idx="0"/>
  <rigid_body x="0.10915367535944488 0.004999415425076322" theta="1.570796326794897" v="0.11385971005079787 0.47076000333613455" omega="0" rho="8.0" r="1" geo_idx="0"/>
  <rigid_body x="0.10708051093527182 0.10832280761206474" theta="1.570796326794897" v="-0.6849321971126627 0.0350851566743684" omega="0" rho="8.0" r="1" geo_idx="0"/>
  <rigid_body x="0.10523514760041389 0.20186114517026973" theta="1.570796326794897" v="-0.5086523243416718 -0.4076475818959553" omega="0" rho="8.0" r="1" geo_idx="0"/>
  <rigid_body x="0.2085674702930263 0.007502848343988825" theta="1.570796326794897" v="-0.21206561096476917 -0.663675772822027" omega="0" rho="8.0" r="1" geo_idx="0"/>
  <rigid_body x="0.20232178894648856 0.10668835805148359" theta="1.570796326794897" v="0.9983694923167299 -0.45700854134755" omega="0" rho="8.0" r="1" geo_idx="0"/>
  <rigid_body x="0.20685588905284807 0.2018801951968261" theta="1.570796326794897" v="-0.7519620643881355 -0.5813562435539785" omega="0" rho="8.0" r="1" geo_idx="0"/>
    
    </rigidbody2d_scene>
    