
    <rigidbody2d_scene>
    
      <camera center="0 0" scale="8.3225" fps="50" render_at_fps="0" locked="0"/>
    
      <integrator type="symplectic_euler" dt="0.01"/>
    
      <impact_operator type="gr" CoR="1.0" v_tol="1.0e-9" cache_impulses="0">
        <solver name="lcp_solver_isaiah_debug" linear_solvers="ma27 ma86" max_iters="100" tol="1.0e-6"/>
      </impact_operator>
    
      <near_earth_gravity f="0.0 0.0"/>
    
    
      <geometry type="circle" r="1"/>
    
      <rigid_body x="0.0019270492874990987 0.006080086962243422" theta="1.570796326794897" v="0.7515051866612081 0.03373608761417857" omega="0" rho="8.0" r="1" geo_idx="0"/>
  <rigid_body x="0.0063071880326373 0.10074238036253691" theta="1.570796326794897" v="0.7957692179057947 -0.7031269812302505" omega="0" rho="8.0" r="1" geo_idx="0"/>
  <rigid_body x="0.003386338551620535 0.2080801762356831" theta="1.570796326794897" v="-0.829983530141019 -0.60941059396646" omega="0" rho="8.0" r="1" geo_idx="0"/>
  <rigid_body x="0.10694988654852851 0.0034531200713437196" theta="1.570796326794897" v="0.5960967723305515 0.43949689377162815" omega="0" rho="8.0" r="1" geo_idx="0"/>
  <rigid_body x="0.10146976214342833 0.10907832434819176" theta="1.570796326794897" v="0.6121434439408522 0.06257950368749055" omega="0" rho="8.0" r="1" geo_idx="0"/>
  <rigid_body x="0.1041680126502474 0.20705716232691515" theta="1.570796326794897" v="0.8617571078863548 -0.5782565131035056" omega="0" rho="8.0" r="1" geo_idx="0"/>
  <rigid_body x="0.20255737528418089 0.009723849579432536" theta="1.570796326794897" v="0.7345333905376179 -0.05937978751653605" omega="0" rho="8.0" r="1" geo_idx="0"/>
  <rigid_body x="0.2033397238799925 0.10200129402747889" theta="1.570796326794897" v="-0.5737839704823586 0.3435460906515615" omega="0" rho="8.0" r="1" geo_idx="0"/>
  <rigid_body x="0.2026131403258268 0.20142443920567168" theta="1.570796326794897" v="0.9947349513272639 0.4613592994034086" omega="0" rho="8.0" r="1" geo_idx="0"/>
    
    </rigidbody2d_scene>
    