
    <rigidbody2d_scene>
    
      <camera center="0 0" scale="8.3225" fps="50" render_at_fps="0" locked="0"/>
    
      <integrator type="symplectic_euler" dt="0.01"/>
    
      <impact_operator type="gr" CoR="1.0" v_tol="1.0e-9" cache_impulses="0">
        <solver name="lcp_solver_isaiah_debug" linear_solvers="ma27 ma86" max_iters="100" tol="1.0e-9"/>
      </impact_operator>
    
      <near_earth_gravity f="0.0 0.0"/>
    
    
      <geometry type="circle" r="1"/>
    
      <rigid_body x="0.00037425420701376114 0.002606906665064588" theta="1.570796326794897" v="-0.16277320573456588 -0.6665078476226516" omega="0" rho="8.0" r="1" geo_idx="0"/>
  <rigid_body x="0.004170646848483598 0.10389070848825033" theta="1.570796326794897" v="-0.1080333414773853 0.9144113359657704" omega="0" rho="8.0" r="1" geo_idx="0"/>
  <rigid_body x="0.009153104064691678 0.20548060452705713" theta="1.570796326794897" v="0.23156713434949094 -0.8128803342706108" omega="0" rho="8.0" r="1" geo_idx="0"/>
  <rigid_body x="0.10782804266504101 0.008161165109082987" theta="1.570796326794897" v="0.15665225251471537 -0.5192110389295521" omega="0" rho="8.0" r="1" geo_idx="0"/>
  <rigid_body x="0.10037949205896671 0.10753399375786822" theta="1.570796326794897" v="-0.608215070930149 -0.8906104174735094" omega="0" rho="8.0" r="1" geo_idx="0"/>
  <rigid_body x="0.10341234104870425 0.2089280376172087" theta="1.570796326794897" v="-0.11702473588163698 0.8249165899995328" omega="0" rho="8.0" r="1" geo_idx="0"/>
  <rigid_body x="0.20610102951741174 0.0026943282271922743" theta="1.570796326794897" v="0.24615689487895387 -0.7664346938862241" omega="0" rho="8.0" r="1" geo_idx="0"/>
  <rigid_body x="0.2066530042663583 0.10226056792523314" theta="1.570796326794897" v="-0.12631727870058707 0.16443451368583517" omega="0" rho="8.0" r="1" geo_idx="0"/>
  <rigid_body x="0.20975882381914762 0.2053715674526068" theta="1.570796326794897" v="0.41516814278134007 -0.8887398193652716" omega="0" rho="8.0" r="1" geo_idx="0"/>
    
    </rigidbody2d_scene>
    