
    <rigidbody2d_scene>
    
      <camera center="0 0" scale="8.3225" fps="50" render_at_fps="0" locked="0"/>
    
      <integrator type="symplectic_euler" dt="0.01"/>
    
      <impact_operator type="gr" CoR="1.0" v_tol="1.0e-9" cache_impulses="0">
        <solver name="lcp_solver_isaiah_debug" linear_solvers="ma27 ma86" max_iters="100" tol="1.0e-6"/>
      </impact_operator>
    
      <near_earth_gravity f="0.0 0.0"/>
    
    
      <geometry type="circle" r="1"/>
    
      <rigid_body x="0.005524065995369383 0.0066966061957751165" theta="1.570796326794897" v="-0.4948651802778026 0.34655635440561317" omega="0" rho="8.0" r="1" geo_idx="0"/>
  <rigid_body x="0.0015885038589856938 0.10533899337530965" theta="1.570796326794897" v="0.13092860947831197 0.09967042950381955" omega="0" rho="8.0" r="1" geo_idx="0"/>
  <rigid_body x="0.008517968471529287 0.20302266120323723" theta="1.570796326794897" v="-0.808971874067298 0.5479133806592345" omega="0" rho="8.0" r="1" geo_idx="0"/>
  <rigid_body x="0.10862330267883155 0.006052529403526895" theta="1.570796326794897" v="-0.652137254146234 -0.6106356216914177" omega="0" rho="8.0" r="1" geo_idx="0"/>
  <rigid_body x="0.10227575383321753 0.1056976925225163" theta="1.570796326794897" v="-0.8085212653213576 0.6615434296037213" omega="0" rho="8.0" r="1" geo_idx="0"/>
  <rigid_body x="0.10248867787361945 0.202342934391429" theta="1.570796326794897" v="-0.4723567528579484 -0.7055610130752901" omega="0" rho="8.0" r="1" geo_idx="0"/>
  <rigid_body x="0.2007598586678812 0.009802755923753825" theta="1.570796326794897" v="-0.20525300762954135 0.3597212161591401" omega="0" rho="8.0" r="1" geo_idx="0"/>
  <rigid_body x="0.20219740133559422 0.10811774089900794" theta="1.570796326794897" v="-0.08658630381331545 -0.41207981704625807" omega="0" rho="8.0" r="1" geo_idx="0"/>
  <rigid_body x="0.20919746286019675 0.20969392968903255" theta="1.570796326794897" v="-0.8158682639089672 -0.5134171585401492" omega="0" rho="8.0" r="1" geo_idx="0"/>
    
    </rigidbody2d_scene>
    