
    <rigidbody2d_scene>
    
      <camera center="0 0" scale="8.3225" fps="50" render_at_fps="0" locked="0"/>
    
      <integrator type="symplectic_euler" dt="0.01"/>
    
      <impact_operator type="gr" CoR="1.0" v_tol="1.0e-9" cache_impulses="0">
        <solver name="lcp_solver_isaiah_debug" linear_solvers="ma27 ma86" max_iters="100" tol="1.0e-9"/>
      </impact_operator>
    
      <near_earth_gravity f="0.0 0.0"/>
    
    
      <geometry type="circle" r="1"/>
    
      <rigid_body x="0.009525861031838084 0.008141940151992938" theta="1.570796326794897" v="-0.364499457135568 -0.4588762291185793" omega="0" rho="8.0" r="1" geo_idx="0"/>
  <rigid_body x="0.008672482734493166 0.10572768228477436" theta="1.570796326794897" v="-0.4283460497469671 -0.47157660405114465" omega="0" rho="8.0" r="1" geo_idx="0"/>
  <rigid_body x="0.0086147735459069 0.20994671963174355" theta="1.570796326794897" v="-0.5742454723984916 -0.8515717469470725" omega="0" rho="8.0" r="1" geo_idx="0"/>
  <rigid_body x="0.10895826883913944 0.008939603413854937" theta="1.570796326794897" v="-0.30424584416373435 -0.0720690921237872" omega="0" rho="8.0" r="1" geo_idx="0"/>
  <rigid_body x="0.10879078243995824 0.10854923764013628" theta="1.570796326794897" v="0.05372394941820735 0.9897443505620429" omega="0" rho="8.0" r="1" geo_idx="0"/>
  <rigid_body x="0.1012712473821391 0.20910578858862394" theta="1.570796326794897" v="-0.3908332052960972 -0.4397415122173922" omega="0" rho="8.0" r="1" geo_idx="0"/>
  <rigid_body x="0.2024964766752684 0.004123757486029721" theta="1.570796326794897" v="0.7203963481271056 -0.6324145100016207" omega="0" rho="8.0" r="1" geo_idx="0"/>
  <rigid_body x="0.20367372955549748 0.10352259723954929" theta="1.570796326794897" v="0.04619822424084896 -0.38932467974220164" omega="0" rho="8.0" r="1" geo_idx="0"/>
  <rigid_body x="0.2077105891476121 0.20981420021761504" theta="1.570796326794897" v="-0.6145727593580783 -0.20823277596637113" omega="0" rho="8.0" r="1" geo_idx="0"/>
    
    </rigidbody2d_scene>
    