
    <rigidbody2d_scene>
    
      <camera center="0 0" scale="8.3225" fps="50" render_at_fps="0" locked="0"/>
    
      <integrator type="symplectic_euler" dt="0.01"/>
    
      <impact_operator type="gr" CoR="1.0" v_tol="1.0e-9" cache_impulses="0">
        <solver name="lcp_solver_isaiah_debug" linear_solvers="ma27 ma86" max_iters="100" tol="1.0e-9"/>
      </impact_operator>
    
      <near_earth_gravity f="0.0 0.0"/>
    
    
      <geometry type="circle" r="1"/>
    
      <rigid_body x="0.003604232451931908 0.0029214239366788007" theta="1.570796326794897" v="-0.380150022832743 0.30035782449346193" omega="0" rho="8.0" r="1" geo_idx="0"/>
  <rigid_body x="0.008544052273179684 0.10158174565927541" theta="1.570796326794897" v="-0.2659337963961803 0.9733036630495104" omega="0" rho="8.0" r="1" geo_idx="0"/>
  <rigid_body x="0.0028908536519089223 0.2043780052665103" theta="1.570796326794897" v="0.3094396851364629 0.5386054995985983" omega="0" rho="8.0" r="1" geo_idx="0"/>
  <rigid_body x="0.10350088385317134 0.0012469375701216101" theta="1.570796326794897" v="-0.8760777617842026 0.530413363843885" omega="0" rho="8.0" r="1" geo_idx="0"/>
  <rigid_body x="0.10339773954881906 0.10903183586867948" theta="1.570796326794897" v="-0.7042277291466195 0.23976902751599716" omega="0" rho="8.0" r="1" geo_idx="0"/>
  <rigid_body x="0.1088491373870706 0.207303792400057" theta="1.570796326794897" v="0.2646508088494608 0.5188695460218538" omega="0" rho="8.0" r="1" geo_idx="0"/>
  <rigid_body x="0.20584877405873242 0.006551233615290304" theta="1.570796326794897" v="0.7446407349408974 -0.6474717579927702" omega="0" rho="8.0" r="1" geo_idx="0"/>
  <rigid_body x="0.20740088178008315 0.10882320280418298" theta="1.570796326794897" v="-0.9959124527705925 0.34349202310907834" omega="0" rho="8.0" r="1" geo_idx="0"/>
  <rigid_body x="0.20489909341705803 0.20892780757168727" theta="1.570796326794897" v="0.9747730765181761 0.08193778667841523" omega="0" rho="8.0" r="1" geo_idx="0"/>
    
    </rigidbody2d_scene>
    