
    <rigidbody2d_scene>
    
      <camera center="0 0" scale="8.3225" fps="50" render_at_fps="0" locked="0"/>
    
      <integrator type="symplectic_euler" dt="0.01"/>
    
      <impact_operator type="gr" CoR="1.0" v_tol="1.0e-12" cache_impulses="0">
        <solver name="lcp_solver_isaiah_debug" linear_solvers="ma27 ma86" max_iters="100" tol="1.0e-12"/>
      </impact_operator>
    
      <near_earth_gravity f="0.0 0.0"/>
    
    
      <geometry type="circle" r="1"/>
    
      <rigid_body x="0.006629592241046381 0.0032217241176660185" theta="0" v="-0.22649721708591564 -0.051744000617995445" omega="0" rho="0.3183098861837907" r="1" geo_idx="0"/>
  <rigid_body x="0.009696775182703453 1.001024557679789" theta="0" v="-0.1378408283246464 -0.08035797208648399" omega="0" rho="0.3183098861837907" r="1" geo_idx="0"/>
  <rigid_body x="0.007482673322227379 2.0014963643282444" theta="0" v="0.18468019551891257 0.5732920102779968" omega="0" rho="0.3183098861837907" r="1" geo_idx="0"/>
  <rigid_body x="1.0009388776507184 0.0011666311676969932" theta="0" v="0.6055870265203618 0.8505280849777586" omega="0" rho="0.3183098861837907" r="1" geo_idx="0"/>
  <rigid_body x="1.0009182037683844 1.0098480332073902" theta="0" v="-0.24931667824863557 0.9316905910499349" omega="0" rho="0.3183098861837907" r="1" geo_idx="0"/>
  <rigid_body x="1.0085434870025425 2.0083300298404034" theta="0" v="-0.4051052086598501 -0.657728562802192" omega="0" rho="0.3183098861837907" r="1" geo_idx="0"/>
  <rigid_body x="2.0065877253625417 0.0006920147467455362" theta="0" v="-0.4874682456660395 0.7921556923894237" omega="0" rho="0.3183098861837907" r="1" geo_idx="0"/>
  <rigid_body x="2.0018412646567283 1.0000529045084114" theta="0" v="0.2358792876014848 0.6713679712789007" omega="0" rho="0.3183098861837907" r="1" geo_idx="0"/>
  <rigid_body x="2.006764951254085 2.0064148865039364" theta="0" v="-0.58468304999499 -0.5500089582738219" omega="0" rho="0.3183098861837907" r="1" geo_idx="0"/>
    
    </rigidbody2d_scene>
    