
    <rigidbody2d_scene>
    
      <camera center="0 0" scale="8.3225" fps="50" render_at_fps="0" locked="0"/>
    
      <integrator type="symplectic_euler" dt="0.01"/>
    
      <impact_operator type="gr" CoR="1.0" v_tol="1.0e-12" cache_impulses="0">
        <solver name="lcp_solver_isaiah_debug" linear_solvers="ma27 ma86" max_iters="100" tol="1.0e-12"/>
      </impact_operator>
    
      <near_earth_gravity f="0.0 0.0"/>
    
    
      <geometry type="circle" r="1"/>
    
      <rigid_body x="0.009761541195683244 0.004003045985125558" theta="0" v="0.24084532625902377 0.8401824713807895" omega="0" rho="0.3183098861837907" r="1" geo_idx="0"/>
  <rigid_body x="0.007005288096847664 1.0092082132968978" theta="0" v="-0.9304816695269023 -0.38549224988804753" omega="0" rho="0.3183098861837907" r="1" geo_idx="0"/>
  <rigid_body x="0.009313740300841717 2.0059981133586384" theta="0" v="0.10652295260959943 0.6595364829890391" omega="0" rho="0.3183098861837907" r="1" geo_idx="0"/>
  <rigid_body x="0.007637053433382896 3.008001672557211" theta="0" v="0.5308618398377538 0.834547027606366" omega="0" rho="0.3183098861837907" r="1" geo_idx="0"/>
  <rigid_body x="0.003194860634830321 4.005927126078094" theta="0" v="-0.911460563565123 0.18252895534013525" omega="0" rho="0.3183098861837907" r="1" geo_idx="0"/>
  <rigid_body x="0.008439767154207953 5.002437710430914" theta="0" v="-0.9368659574768508 -0.7501333164463475" omega="0" rho="0.3183098861837907" r="1" geo_idx="0"/>
  <rigid_body x="0.0016963572114196668 6.006344823611097" theta="0" v="-0.30705223066223275 0.3090438456837834" omega="0" rho="0.3183098861837907" r="1" geo_idx="0"/>
  <rigid_body x="1.0041184479859806 0.009324588636184709" theta="0" v="0.20319303265105404 -0.05880057555231022" omega="0" rho="0.3183098861837907" r="1" geo_idx="0"/>
  <rigid_body x="1.00224199425263 1.003462061234699" theta="0" v="-0.596453088098496 -0.4188103416860183" omega="0" rho="0.3183098861837907" r="1" geo_idx="0"/>
  <rigid_body x="1.008524148218193 2.000800845995929" theta="0" v="-0.12448815565186155 0.01757984251730571" omega="0" rho="0.3183098861837907" r="1" geo_idx="0"/>
  <rigid_body x="1.0062433601400709 3.006513507931917" theta="0" v="-0.12406262372890331 0.7922780336369029" omega="0" rho="0.3183098861837907" r="1" geo_idx="0"/>
  <rigid_body x="1.0077462744901438 4.0076293704549775" theta="0" v="0.9527920550232374 -0.15578918575799827" omega="0" rho="0.3183098861837907" r="1" geo_idx="0"/>
  <rigid_body x="1.007981595690572 5.004831627978371" theta="0" v="-0.8686519822438379 -0.1540057672701427" omega="0" rho="0.3183098861837907" r="1" geo_idx="0"/>
  <rigid_body x="1.0023935089064986 6.007864457965221" theta="0" v="0.8942966767885612 -0.08055397239539741" omega="0" rho="0.3183098861837907" r="1" geo_idx="0"/>
  <rigid_body x="2.005869604910987 0.0036307519839848903" theta="0" v="-0.6407891141399211 0.23528828526521073" omega="0" rho="0.3183098861837907" r="1" geo_idx="0"/>
  <rigid_body x="2.0029266691369907 1.0019392377153489" theta="0" v="-0.8879869912670504 -0.7540797780730588" omega="0" rho="0.3183098861837907" r="1" geo_idx="0"/>
  <rigid_body x="2.0007522736518593 2.0050500257553012" theta="0" v="0.09699500973308983 0.9536978364770696" omega="0" rho="0.3183098861837907" r="1" geo_idx="0"/>
  <rigid_body x="2.0041360788431635 3.000198741144214" theta="0" v="-0.2862692850987043 0.07544952773760394" omega="0" rho="0.3183098861837907" r="1" geo_idx="0"/>
  <rigid_body x="2.0095532561139677 4.0046452029242765" theta="0" v="0.9180150573814001 -0.7060104513410301" omega="0" rho="0.3183098861837907" r="1" geo_idx="0"/>
  <rigid_body x="2.0001504900981657 5.007348056030599" theta="0" v="0.55109880075722 -0.3204448091455463" omega="0" rho="0.3183098861837907" r="1" geo_idx="0"/>
  <rigid_body x="2.003421564472105 6.004130236052613" theta="0" v="-0.20038820216033293 0.21461942495401765" omega="0" rho="0.3183098861837907" r="1" geo_idx="0"/>
  <rigid_body x="3.0078120621525155 0.003528923628456667" theta="0" v="-0.7561812864820376 -0.2297909986177753" omega="0" rho="0.3183098861837907" r="1" geo_idx="0"/>
  <rigid_body x="3.001333473680871 1.0024504041666549" theta="0" v="-0.7886697811810326 0.89496553563375" omega="0" rho="0.3183098861837907" r="1" geo_idx="0"/>
  <rigid_body x="3.0031806805394288 2.0011703330921744" theta="0" v="-0.8156423900430632 0.8576142574333179" omega="0" rho="0.3183098861837907" r="1" geo_idx="0"/>
  <rigid_body x="3.0004317863455277 3.0071097883917437" theta="0" v="0.5982364021281803 -0.8317302353688663" omega="0" rho="0.3183098861837907" r="1" geo_idx="0"/>
  <rigid_body x="3.0021899538494536 4.00377141906011" theta="0" v="0.6277134439674497 -0.3860352333293495" omega="0" rho="0.3183098861837907" r="1" geo_idx="0"/>
  <rigid_body x="3.0041392746971063 5.0046879011118826" theta="0" v="0.7822121612280717 -0.3828037733929084" omega="0" rho="0.3183098861837907" r="1" geo_idx="0"/>
  <rigid_body x="3.0078601098160056 6.009140420715142" theta="0" v="-0.24784923113893842 -0.10714342247676334" omega="0" rho="0.3183098861837907" r="1" geo_idx="0"/>
  <rigid_body x="4.007596156447507 0.001999242945554313" theta="0" v="-0.5198566944251868 0.10539962018776783" omega="0" rho="0.3183098861837907" r="1" geo_idx="0"/>
  <rigid_body x="4.0069151321389125 1.0016811812407456" theta="0" v="-0.9998328292255478 -0.8352719681693843" omega="0" rho="0.3183098861837907" r="1" geo_idx="0"/>
  <rigid_body x="4.003246131391913 2.003633223281936" theta="0" v="0.43792789822413214 0.2946191607709787" omega="0" rho="0.3183098861837907" r="1" geo_idx="0"/>
  <rigid_body x="4.00505110739574 3.006472369341173" theta="0" v="0.4570714078703657 -0.3481559993598051" omega="0" rho="0.3183098861837907" r="1" geo_idx="0"/>
  <rigid_body x="4.009871700741033 4.0075443328723965" theta="0" v="0.4622335134620721 -0.05236519279822294" omega="0" rho="0.3183098861837907" r="1" geo_idx="0"/>
  <rigid_body x="4.001250803801663 5.003625868394956" theta="0" v="0.25013971127263757 -0.3075755350543803" omega="0" rho="0.3183098861837907" r="1" geo_idx="0"/>
  <rigid_body x="4.003208413527317 6.002424600859639" theta="0" v="0.9245821399479333 -0.20769456409768083" omega="0" rho="0.3183098861837907" r="1" geo_idx="0"/>
  <rigid_body x="5.003215389108002 0.0001689086566189213" theta="0" v="0.0712288431097221 0.77026583108243" omega="0" rho="0.3183098861837907" r="1" geo_idx="0"/>
  <rigid_body x="5.00673566693717 1.0006717424803164" theta="0" v="0.8784795560501706 0.37059934898054725" omega="0" rho="0.3183098861837907" r="1" geo_idx="0"/>
  <rigid_body x="5.002382499357533 2.00742091259747" theta="0" v="-0.9728375718667897 -0.24784382547282968" omega="0" rho="0.3183098861837907" r="1" geo_idx="0"/>
  <rigid_body x="5.006069504313284 3.0094198032843953" theta="0" v="-0.7669543743036631 -0.7886010754094439" omega="0" rho="0.3183098861837907" r="1" geo_idx="0"/>
  <rigid_body x="5.004057349910341 4.000099909046536" theta="0" v="-0.7031833810879871 0.08606355535013455" omega="0" rho="0.3183098861837907" r="1" geo_idx="0"/>
  <rigid_body x="5.006140217298309 5.002916290089595" theta="0" v="0.8429893015630412 -0.2540629017046656" omega="0" rho="0.3183098861837907" r="1" geo_idx="0"/>
  <rigid_body x="5.0055155675032985 6.005819123797234" theta="0" v="0.9473732376243895 -0.9804502520086784" omega="0" rho="0.3183098861837907" r="1" geo_idx="0"/>
  <rigid_body x="6.001747367353083 0.008074244773755079" theta="0" v="0.24722968328568995 -0.8626316870602353" omega="0" rho="0.3183098861837907" r="1" geo_idx="0"/>
  <rigid_body x="6.000293721155582 1.0078300368365676" theta="0" v="-0.6864894383323361 0.3891977147378429" omega="0" rho="0.3183098861837907" r="1" geo_idx="0"/>
  <rigid_body x="6.005961900472875 2.004343230700774" theta="0" v="-0.3663866491639609 0.06420781300522593" omega="0" rho="0.3183098861837907" r="1" geo_idx="0"/>
  <rigid_body x="6.007342875019286 3.002404809685835" theta="0" v="0.2632797408110845 -0.8591449274866609" omega="0" rho="0.3183098861837907" r="1" geo_idx="0"/>
  <rigid_body x="6.007753974502753 4.006508211548921" theta="0" v="-0.6712570161948426 0.5942769735221312" omega="0" rho="0.3183098861837907" r="1" geo_idx="0"/>
  <rigid_body x="6.008060103242834 5.00073867614911" theta="0" v="0.8378449373843548 -0.14828145129391435" omega="0" rho="0.3183098861837907" r="1" geo_idx="0"/>
  <rigid_body x="6.001024039634437 6.007588371676075" theta="0" v="-0.15644693310509328 0.6504276614489066" omega="0" rho="0.3183098861837907" r="1" geo_idx="0"/>
    
    </rigidbody2d_scene>
    