
    <rigidbody2d_scene>
    
      <camera center="0 0" scale="8.3225" fps="50" render_at_fps="0" locked="0"/>
    
      <integrator type="symplectic_euler" dt="0.01"/>
    
      <impact_operator type="gr" CoR="1.0" v_tol="1.0e-9" cache_impulses="0">
        <solver name="lcp_solver_isaiah_debug" linear_solvers="ma27 ma86" max_iters="100" tol="1.0e-9"/>
      </impact_operator>
    
      <near_earth_gravity f="0.0 0.0"/>
    
    
      <geometry type="circle" r="1"/>
    
      <rigid_body x="0.004871839886004837 0.0021061126471009282" theta="0" v="-0.44633574108594076 0.3640664411024688" omega="0" rho="0.3183098861837907" r="1" geo_idx="0"/>
  <rigid_body x="0.007701297644578004 0.10373916168704728" theta="0" v="0.6309961075597212 -0.2734266334263147" omega="0" rho="0.3183098861837907" r="1" geo_idx="0"/>
  <rigid_body x="0.10532600186938246 5.7058995293231e-05" theta="0" v="-0.46134509719637395 0.44275537801404874" omega="0" rho="0.3183098861837907" r="1" geo_idx="0"/>
  <rigid_body x="0.10561557853146955 0.10250815959620171" theta="0" v="-0.30872806301073075 0.029480101391711644" omega="0" rho="0.3183098861837907" r="1" geo_idx="0"/>
    
    </rigidbody2d_scene>
    