
    <rigidbody2d_scene>
    
      <camera center="0 0" scale="8.3225" fps="50" render_at_fps="0" locked="0"/>
    
      <integrator type="symplectic_euler" dt="0.01"/>
    
      <impact_operator type="gr" CoR="1.0" v_tol="1.0e-9" cache_impulses="0">
        <solver name="lcp_solver_isaiah_debug" linear_solvers="ma27 ma86" max_iters="100" tol="1.0e-6"/>
      </impact_operator>
    
      <near_earth_gravity f="0.0 0.0"/>
    
    
      <geometry type="circle" r="1"/>
    
      <rigid_body x="0.00412411106270263 0.00766670942362305" theta="0" v="-0.2961037239846911 -0.4313045167932372" omega="0" rho="0.3183098861837907" r="1" geo_idx="0"/>
  <rigid_body x="0.0008677195057497667 0.10846738692571828" theta="0" v="-0.09838695855674295 -0.07651975338812034" omega="0" rho="0.3183098861837907" r="1" geo_idx="0"/>
  <rigid_body x="0.10052390568369304 0.0006418815517092868" theta="0" v="0.5632381699587996 -0.7803643722509559" omega="0" rho="0.3183098861837907" r="1" geo_idx="0"/>
  <rigid_body x="0.10249270692113312 0.1075457946862449" theta="0" v="-0.8243272931871559 0.07932633640333875" omega="0" rho="0.3183098861837907" r="1" geo_idx="0"/>
    
    </rigidbody2d_scene>
    