
    <rigidbody2d_scene>
    
      <camera center="0 0" scale="8.3225" fps="50" render_at_fps="0" locked="0"/>
    
      <integrator type="symplectic_euler" dt="0.01"/>
    
      <impact_operator type="gr" CoR="1.0" v_tol="1.0e-9" cache_impulses="0">
        <solver name="lcp_solver_isaiah_debug" linear_solvers="ma27 ma86" max_iters="100" tol="1.0e-6"/>
      </impact_operator>
    
      <near_earth_gravity f="0.0 0.0"/>
    
    
      <geometry type="circle" r="1"/>
    
      <rigid_body x="0.002497055795369808 0.005694219179898009" theta="0" v="0.35429880738772 0.0042240439919611905" omega="0" rho="0.3183098861837907" r="1" geo_idx="0"/>
  <rigid_body x="0.003851047482632717 0.10656664909406889" theta="0" v="0.1239319735560489 0.8039185840809939" omega="0" rho="0.3183098861837907" r="1" geo_idx="0"/>
  <rigid_body x="0.10449874932567171 0.006757398719382356" theta="0" v="0.08616837214216533 0.6146045450856767" omega="0" rho="0.3183098861837907" r="1" geo_idx="0"/>
  <rigid_body x="0.10402854823717723 0.10147298410104487" theta="0" v="-0.8057605637596892 -0.9179674021079967" omega="0" rho="0.3183098861837907" r="1" geo_idx="0"/>
    
    </rigidbody2d_scene>
    