
    <rigidbody2d_scene>
    
      <camera center="0 0" scale="8.3225" fps="50" render_at_fps="0" locked="0"/>
    
      <integrator type="symplectic_euler" dt="0.01"/>
    
      <impact_operator type="gr" CoR="1.0" v_tol="1.0e-9" cache_impulses="0">
        <solver name="lcp_solver_isaiah_debug" linear_solvers="ma27 ma86" max_iters="100" tol="1.0e-9"/>
      </impact_operator>
    
      <near_earth_gravity f="0.0 0.0"/>
    
    
      <geometry type="circle" r="1"/>
    
      <rigid_body x="0.003994947959697914 0.008957839057265783" theta="0" v="0.7272334510331822 0.7720543013004058" omega="0" rho="0.3183098861837907" r="1" geo_idx="0"/>
  <rigid_body x="0.004285301653412327 0.10509161299913498" theta="0" v="0.005092796119952947 0.11151471318514972" omega="0" rho="0.3183098861837907" r="1" geo_idx="0"/>
  <rigid_body x="0.10688716620592875 0.005836526023480813" theta="0" v="-0.631556959609028 0.11465065256892126" omega="0" rho="0.3183098861837907" r="1" geo_idx="0"/>
  <rigid_body x="0.1026900528822308 0.1061539932882001" theta="0" v="0.7205725119161237 0.06740136512172668" omega="0" rho="0.3183098861837907" r="1" geo_idx="0"/>
    
    </rigidbody2d_scene>
    