
    <rigidbody2d_scene>
    
      <camera center="0 0" scale="8.3225" fps="50" render_at_fps="0" locked="0"/>
    
      <integrator type="symplectic_euler" dt="0.01"/>
    
      <impact_operator type="gr" CoR="1.0" v_tol="1.0e-9" cache_impulses="0">
        <solver name="lcp_solver_isaiah_debug" linear_solvers="ma27 ma86" max_iters="100" tol="1.0e-6"/>
      </impact_operator>
    
      <near_earth_gravity f="0.0 0.0"/>
    
    
      <geometry type="circle" r="1"/>
    
      <rigid_body x="0.009796348535601808 0.009382614004690521" theta="0" v="-0.7749074849863726 -0.29301876516932635" omega="0" rho="0.3183098861837907" r="1" geo_idx="0"/>
  <rigid_body x="0.004472668086569075 0.10191493866379908" theta="0" v="0.31841839758115387 0.013693697906458802" omega="0" rho="0.3183098861837907" r="1" geo_idx="0"/>
  <rigid_body x="0.10078327526177781 0.0024449743615855522" theta="0" v="0.04562823754314027 -0.7929761886113385" omega="0" rho="0.3183098861837907" r="1" geo_idx="0"/>
  <rigid_body x="0.1082097459342443 0.10356785699295419" theta="0" v="0.04133572450952805 0.3529430424231377" omega="0" rho="0.3183098861837907" r="1" geo_idx="0"/>
    
    </rigidbody2d_scene>
    